{
  "timestamp": "20260511_142725",
  "data": {
    "NIFTY": {
      "price": 23997.91,
      "time": "14:27:25",
      "optionsChain": [
        {
          "strikePrice": 23250,
          "isATM": false,
          "CE": {
            "LTP": 190.78,
            "OI": 441846,
            "changeInOI": -2334
          },
          "PE": {
            "LTP": 39.91,
            "OI": 40198,
            "changeInOI": -2203
          }
        },
        {
          "strikePrice": 23300,
          "isATM": false,
          "CE": {
            "LTP": 131.63,
            "OI": 252899,
            "changeInOI": 924
          },
          "PE": {
            "LTP": 135.2,
            "OI": 159454,
            "changeInOI": -2024
          }
        },
        {
          "strikePrice": 23350,
          "isATM": false,
          "CE": {
            "LTP": 114.82,
            "OI": 189540,
            "changeInOI": 3075
          },
          "PE": {
            "LTP": 208.99,
            "OI": 352701,
            "changeInOI": -4476
          }
        },
        {
          "strikePrice": 23400,
          "isATM": false,
          "CE": {
            "LTP": 116.69,
            "OI": 366427,
            "changeInOI": -516
          },
          "PE": {
            "LTP": 161.66,
            "OI": 411626,
            "changeInOI": -1124
          }
        },
        {
          "strikePrice": 23450,
          "isATM": false,
          "CE": {
            "LTP": 46.88,
            "OI": 152408,
            "changeInOI": 227
          },
          "PE": {
            "LTP": 113.7,
            "OI": 181985,
            "changeInOI": 3679
          }
        },
        {
          "strikePrice": 23500,
          "isATM": false,
          "CE": {
            "LTP": 202.31,
            "OI": 247134,
            "changeInOI": -4703
          },
          "PE": {
            "LTP": 206.91,
            "OI": 36105,
            "changeInOI": 3538
          }
        },
        {
          "strikePrice": 23550,
          "isATM": false,
          "CE": {
            "LTP": 59.95,
            "OI": 315541,
            "changeInOI": 3591
          },
          "PE": {
            "LTP": 43.67,
            "OI": 216561,
            "changeInOI": 1435
          }
        },
        {
          "strikePrice": 23600,
          "isATM": false,
          "CE": {
            "LTP": 102.79,
            "OI": 353006,
            "changeInOI": -2570
          },
          "PE": {
            "LTP": 58.63,
            "OI": 120048,
            "changeInOI": -1819
          }
        },
        {
          "strikePrice": 23650,
          "isATM": false,
          "CE": {
            "LTP": 212.84,
            "OI": 107649,
            "changeInOI": -247
          },
          "PE": {
            "LTP": 61.82,
            "OI": 330260,
            "changeInOI": 1004
          }
        },
        {
          "strikePrice": 23700,
          "isATM": false,
          "CE": {
            "LTP": 101.33,
            "OI": 322626,
            "changeInOI": 778
          },
          "PE": {
            "LTP": 122.14,
            "OI": 504544,
            "changeInOI": -1092
          }
        },
        {
          "strikePrice": 23750,
          "isATM": false,
          "CE": {
            "LTP": 101.8,
            "OI": 215602,
            "changeInOI": -1754
          },
          "PE": {
            "LTP": 69.69,
            "OI": 165900,
            "changeInOI": 4264
          }
        },
        {
          "strikePrice": 23800,
          "isATM": false,
          "CE": {
            "LTP": 110.2,
            "OI": 380307,
            "changeInOI": -1852
          },
          "PE": {
            "LTP": 109.42,
            "OI": 287827,
            "changeInOI": -3157
          }
        },
        {
          "strikePrice": 23850,
          "isATM": false,
          "CE": {
            "LTP": 70.75,
            "OI": 112293,
            "changeInOI": 2107
          },
          "PE": {
            "LTP": 166.43,
            "OI": 256264,
            "changeInOI": -3482
          }
        },
        {
          "strikePrice": 23900,
          "isATM": false,
          "CE": {
            "LTP": 123.69,
            "OI": 411804,
            "changeInOI": -3872
          },
          "PE": {
            "LTP": 212.17,
            "OI": 109502,
            "changeInOI": 1907
          }
        },
        {
          "strikePrice": 23950,
          "isATM": false,
          "CE": {
            "LTP": 65.08,
            "OI": 88640,
            "changeInOI": 4578
          },
          "PE": {
            "LTP": 206.73,
            "OI": 375913,
            "changeInOI": -4781
          }
        },
        {
          "strikePrice": 24000,
          "isATM": true,
          "CE": {
            "LTP": 189.87,
            "OI": 503119,
            "changeInOI": -1570
          },
          "PE": {
            "LTP": 138.63,
            "OI": 187335,
            "changeInOI": 4713
          }
        },
        {
          "strikePrice": 24050,
          "isATM": false,
          "CE": {
            "LTP": 68.63,
            "OI": 249777,
            "changeInOI": 3390
          },
          "PE": {
            "LTP": 126.38,
            "OI": 355909,
            "changeInOI": 1303
          }
        },
        {
          "strikePrice": 24100,
          "isATM": false,
          "CE": {
            "LTP": 121.01,
            "OI": 489219,
            "changeInOI": -1410
          },
          "PE": {
            "LTP": 151.24,
            "OI": 140738,
            "changeInOI": -4983
          }
        },
        {
          "strikePrice": 24150,
          "isATM": false,
          "CE": {
            "LTP": 104.97,
            "OI": 388549,
            "changeInOI": 4627
          },
          "PE": {
            "LTP": 119.03,
            "OI": 483363,
            "changeInOI": 2307
          }
        },
        {
          "strikePrice": 24200,
          "isATM": false,
          "CE": {
            "LTP": 67.76,
            "OI": 37739,
            "changeInOI": -1133
          },
          "PE": {
            "LTP": 64.05,
            "OI": 470174,
            "changeInOI": -3009
          }
        },
        {
          "strikePrice": 24250,
          "isATM": false,
          "CE": {
            "LTP": 189.4,
            "OI": 23689,
            "changeInOI": 2498
          },
          "PE": {
            "LTP": 172.26,
            "OI": 473696,
            "changeInOI": -23
          }
        },
        {
          "strikePrice": 24300,
          "isATM": false,
          "CE": {
            "LTP": 72.57,
            "OI": 276704,
            "changeInOI": 4826
          },
          "PE": {
            "LTP": 122.46,
            "OI": 355971,
            "changeInOI": 3985
          }
        },
        {
          "strikePrice": 24350,
          "isATM": false,
          "CE": {
            "LTP": 149.59,
            "OI": 194948,
            "changeInOI": -1403
          },
          "PE": {
            "LTP": 193.46,
            "OI": 85599,
            "changeInOI": -2308
          }
        },
        {
          "strikePrice": 24400,
          "isATM": false,
          "CE": {
            "LTP": 156.72,
            "OI": 133247,
            "changeInOI": 420
          },
          "PE": {
            "LTP": 142.12,
            "OI": 40869,
            "changeInOI": 2845
          }
        },
        {
          "strikePrice": 24450,
          "isATM": false,
          "CE": {
            "LTP": 75.92,
            "OI": 498058,
            "changeInOI": -1089
          },
          "PE": {
            "LTP": 173.38,
            "OI": 173705,
            "changeInOI": -2409
          }
        },
        {
          "strikePrice": 24500,
          "isATM": false,
          "CE": {
            "LTP": 148.15,
            "OI": 9134,
            "changeInOI": -4087
          },
          "PE": {
            "LTP": 125.17,
            "OI": 402101,
            "changeInOI": -4584
          }
        },
        {
          "strikePrice": 24550,
          "isATM": false,
          "CE": {
            "LTP": 194.35,
            "OI": 120255,
            "changeInOI": 1050
          },
          "PE": {
            "LTP": 142.22,
            "OI": 316213,
            "changeInOI": -3948
          }
        },
        {
          "strikePrice": 24600,
          "isATM": false,
          "CE": {
            "LTP": 211.2,
            "OI": 441223,
            "changeInOI": -1996
          },
          "PE": {
            "LTP": 49.01,
            "OI": 20602,
            "changeInOI": -1816
          }
        },
        {
          "strikePrice": 24650,
          "isATM": false,
          "CE": {
            "LTP": 71.17,
            "OI": 193222,
            "changeInOI": -3284
          },
          "PE": {
            "LTP": 78.84,
            "OI": 135133,
            "changeInOI": 2969
          }
        },
        {
          "strikePrice": 24700,
          "isATM": false,
          "CE": {
            "LTP": 115.16,
            "OI": 364981,
            "changeInOI": 1395
          },
          "PE": {
            "LTP": 177.5,
            "OI": 231207,
            "changeInOI": -3722
          }
        }
      ]
    },
    "BANKNIFTY": {
      "price": 48001.4,
      "time": "14:27:25",
      "optionsChain": [
        {
          "strikePrice": 46500,
          "isATM": false,
          "CE": {
            "LTP": 190.32,
            "OI": 459204,
            "changeInOI": 550
          },
          "PE": {
            "LTP": 51.61,
            "OI": 203199,
            "changeInOI": 2947
          }
        },
        {
          "strikePrice": 46600,
          "isATM": false,
          "CE": {
            "LTP": 108.69,
            "OI": 318289,
            "changeInOI": -3983
          },
          "PE": {
            "LTP": 96.33,
            "OI": 287189,
            "changeInOI": 1472
          }
        },
        {
          "strikePrice": 46700,
          "isATM": false,
          "CE": {
            "LTP": 64.78,
            "OI": 259322,
            "changeInOI": 1956
          },
          "PE": {
            "LTP": 120.28,
            "OI": 129992,
            "changeInOI": 1487
          }
        },
        {
          "strikePrice": 46800,
          "isATM": false,
          "CE": {
            "LTP": 162.63,
            "OI": 189778,
            "changeInOI": 4252
          },
          "PE": {
            "LTP": 114.89,
            "OI": 227238,
            "changeInOI": 3872
          }
        },
        {
          "strikePrice": 46900,
          "isATM": false,
          "CE": {
            "LTP": 93.84,
            "OI": 385184,
            "changeInOI": -3464
          },
          "PE": {
            "LTP": 142.18,
            "OI": 236436,
            "changeInOI": -2429
          }
        },
        {
          "strikePrice": 47000,
          "isATM": false,
          "CE": {
            "LTP": 136.65,
            "OI": 219953,
            "changeInOI": -2412
          },
          "PE": {
            "LTP": 57.74,
            "OI": 24077,
            "changeInOI": 4855
          }
        },
        {
          "strikePrice": 47100,
          "isATM": false,
          "CE": {
            "LTP": 109.68,
            "OI": 329518,
            "changeInOI": -2066
          },
          "PE": {
            "LTP": 174.1,
            "OI": 213073,
            "changeInOI": -17
          }
        },
        {
          "strikePrice": 47200,
          "isATM": false,
          "CE": {
            "LTP": 189.03,
            "OI": 331078,
            "changeInOI": 754
          },
          "PE": {
            "LTP": 56.16,
            "OI": 469091,
            "changeInOI": 4168
          }
        },
        {
          "strikePrice": 47300,
          "isATM": false,
          "CE": {
            "LTP": 49.23,
            "OI": 202167,
            "changeInOI": 2598
          },
          "PE": {
            "LTP": 142.69,
            "OI": 45175,
            "changeInOI": -4825
          }
        },
        {
          "strikePrice": 47400,
          "isATM": false,
          "CE": {
            "LTP": 141.88,
            "OI": 54911,
            "changeInOI": 308
          },
          "PE": {
            "LTP": 112.38,
            "OI": 178812,
            "changeInOI": 681
          }
        },
        {
          "strikePrice": 47500,
          "isATM": false,
          "CE": {
            "LTP": 192.4,
            "OI": 488300,
            "changeInOI": 2554
          },
          "PE": {
            "LTP": 101.87,
            "OI": 193258,
            "changeInOI": 1185
          }
        },
        {
          "strikePrice": 47600,
          "isATM": false,
          "CE": {
            "LTP": 110.69,
            "OI": 219317,
            "changeInOI": -1266
          },
          "PE": {
            "LTP": 63.87,
            "OI": 429906,
            "changeInOI": -3001
          }
        },
        {
          "strikePrice": 47700,
          "isATM": false,
          "CE": {
            "LTP": 188.94,
            "OI": 249229,
            "changeInOI": -2319
          },
          "PE": {
            "LTP": 157.48,
            "OI": 329405,
            "changeInOI": 3946
          }
        },
        {
          "strikePrice": 47800,
          "isATM": false,
          "CE": {
            "LTP": 109.95,
            "OI": 20841,
            "changeInOI": 3466
          },
          "PE": {
            "LTP": 53.29,
            "OI": 474285,
            "changeInOI": -2474
          }
        },
        {
          "strikePrice": 47900,
          "isATM": false,
          "CE": {
            "LTP": 164.36,
            "OI": 353750,
            "changeInOI": -464
          },
          "PE": {
            "LTP": 170.62,
            "OI": 469557,
            "changeInOI": 3379
          }
        },
        {
          "strikePrice": 48000,
          "isATM": true,
          "CE": {
            "LTP": 80.2,
            "OI": 79489,
            "changeInOI": 942
          },
          "PE": {
            "LTP": 109.37,
            "OI": 20882,
            "changeInOI": 337
          }
        },
        {
          "strikePrice": 48100,
          "isATM": false,
          "CE": {
            "LTP": 139.94,
            "OI": 120393,
            "changeInOI": 2014
          },
          "PE": {
            "LTP": 73.64,
            "OI": 458068,
            "changeInOI": -3989
          }
        },
        {
          "strikePrice": 48200,
          "isATM": false,
          "CE": {
            "LTP": 121.18,
            "OI": 155589,
            "changeInOI": -1105
          },
          "PE": {
            "LTP": 134.98,
            "OI": 91274,
            "changeInOI": -1948
          }
        },
        {
          "strikePrice": 48300,
          "isATM": false,
          "CE": {
            "LTP": 145.3,
            "OI": 294240,
            "changeInOI": -497
          },
          "PE": {
            "LTP": 70.3,
            "OI": 237188,
            "changeInOI": 4600
          }
        },
        {
          "strikePrice": 48400,
          "isATM": false,
          "CE": {
            "LTP": 196.16,
            "OI": 452948,
            "changeInOI": -453
          },
          "PE": {
            "LTP": 120.55,
            "OI": 352456,
            "changeInOI": -1589
          }
        },
        {
          "strikePrice": 48500,
          "isATM": false,
          "CE": {
            "LTP": 84.41,
            "OI": 127686,
            "changeInOI": -3202
          },
          "PE": {
            "LTP": 143.03,
            "OI": 365498,
            "changeInOI": 1365
          }
        },
        {
          "strikePrice": 48600,
          "isATM": false,
          "CE": {
            "LTP": 193.91,
            "OI": 488568,
            "changeInOI": 528
          },
          "PE": {
            "LTP": 138.89,
            "OI": 62735,
            "changeInOI": 2712
          }
        },
        {
          "strikePrice": 48700,
          "isATM": false,
          "CE": {
            "LTP": 152.4,
            "OI": 56299,
            "changeInOI": 2513
          },
          "PE": {
            "LTP": 188.06,
            "OI": 171096,
            "changeInOI": -1807
          }
        },
        {
          "strikePrice": 48800,
          "isATM": false,
          "CE": {
            "LTP": 111.72,
            "OI": 199637,
            "changeInOI": -4031
          },
          "PE": {
            "LTP": 37.0,
            "OI": 463162,
            "changeInOI": 4920
          }
        },
        {
          "strikePrice": 48900,
          "isATM": false,
          "CE": {
            "LTP": 151.05,
            "OI": 376943,
            "changeInOI": 3191
          },
          "PE": {
            "LTP": 176.46,
            "OI": 481295,
            "changeInOI": -1894
          }
        },
        {
          "strikePrice": 49000,
          "isATM": false,
          "CE": {
            "LTP": 198.05,
            "OI": 301723,
            "changeInOI": -2649
          },
          "PE": {
            "LTP": 97.03,
            "OI": 15684,
            "changeInOI": -943
          }
        },
        {
          "strikePrice": 49100,
          "isATM": false,
          "CE": {
            "LTP": 187.89,
            "OI": 200236,
            "changeInOI": -2468
          },
          "PE": {
            "LTP": 191.72,
            "OI": 130539,
            "changeInOI": -3339
          }
        },
        {
          "strikePrice": 49200,
          "isATM": false,
          "CE": {
            "LTP": 159.71,
            "OI": 434637,
            "changeInOI": -172
          },
          "PE": {
            "LTP": 176.55,
            "OI": 100415,
            "changeInOI": 3438
          }
        },
        {
          "strikePrice": 49300,
          "isATM": false,
          "CE": {
            "LTP": 100.27,
            "OI": 349229,
            "changeInOI": -4395
          },
          "PE": {
            "LTP": 155.91,
            "OI": 107295,
            "changeInOI": -363
          }
        },
        {
          "strikePrice": 49400,
          "isATM": false,
          "CE": {
            "LTP": 134.06,
            "OI": 419993,
            "changeInOI": 4618
          },
          "PE": {
            "LTP": 148.11,
            "OI": 9583,
            "changeInOI": 4794
          }
        }
      ]
    }
  }
}