{
  "timestamp": "20260511_151304",
  "data": {
    "NIFTY": {
      "price": 24010.2,
      "time": "15:13:04",
      "optionsChain": [
        {
          "strikePrice": 23250,
          "isATM": false,
          "CE": {
            "LTP": 166.52,
            "OI": 298753,
            "changeInOI": -4541
          },
          "PE": {
            "LTP": 84.49,
            "OI": 607327,
            "changeInOI": 824
          }
        },
        {
          "strikePrice": 23300,
          "isATM": false,
          "CE": {
            "LTP": 89.7,
            "OI": 100289,
            "changeInOI": -129
          },
          "PE": {
            "LTP": 153.58,
            "OI": 356205,
            "changeInOI": 1373
          }
        },
        {
          "strikePrice": 23350,
          "isATM": false,
          "CE": {
            "LTP": 193.0,
            "OI": 398208,
            "changeInOI": 3114
          },
          "PE": {
            "LTP": 72.34,
            "OI": 300958,
            "changeInOI": 2918
          }
        },
        {
          "strikePrice": 23400,
          "isATM": false,
          "CE": {
            "LTP": 156.92,
            "OI": 41729,
            "changeInOI": 3797
          },
          "PE": {
            "LTP": 45.85,
            "OI": 289040,
            "changeInOI": 3853
          }
        },
        {
          "strikePrice": 23450,
          "isATM": false,
          "CE": {
            "LTP": 38.51,
            "OI": 407603,
            "changeInOI": -3289
          },
          "PE": {
            "LTP": 69.31,
            "OI": 474483,
            "changeInOI": -1576
          }
        },
        {
          "strikePrice": 23500,
          "isATM": false,
          "CE": {
            "LTP": 79.75,
            "OI": 322541,
            "changeInOI": 4031
          },
          "PE": {
            "LTP": 160.6,
            "OI": 563900,
            "changeInOI": -3296
          }
        },
        {
          "strikePrice": 23550,
          "isATM": false,
          "CE": {
            "LTP": 45.97,
            "OI": 257365,
            "changeInOI": -131
          },
          "PE": {
            "LTP": 29.61,
            "OI": 70062,
            "changeInOI": 495
          }
        },
        {
          "strikePrice": 23600,
          "isATM": false,
          "CE": {
            "LTP": 181.51,
            "OI": 511340,
            "changeInOI": -249
          },
          "PE": {
            "LTP": 55.84,
            "OI": 367126,
            "changeInOI": 3430
          }
        },
        {
          "strikePrice": 23650,
          "isATM": false,
          "CE": {
            "LTP": 134.82,
            "OI": 292711,
            "changeInOI": 4088
          },
          "PE": {
            "LTP": 187.38,
            "OI": 100041,
            "changeInOI": -949
          }
        },
        {
          "strikePrice": 23700,
          "isATM": false,
          "CE": {
            "LTP": 148.24,
            "OI": 293377,
            "changeInOI": -4166
          },
          "PE": {
            "LTP": 148.84,
            "OI": 324321,
            "changeInOI": 4265
          }
        },
        {
          "strikePrice": 23750,
          "isATM": false,
          "CE": {
            "LTP": 223.57,
            "OI": 322158,
            "changeInOI": -1903
          },
          "PE": {
            "LTP": 167.98,
            "OI": 81059,
            "changeInOI": -2435
          }
        },
        {
          "strikePrice": 23800,
          "isATM": false,
          "CE": {
            "LTP": 219.54,
            "OI": 462366,
            "changeInOI": 746
          },
          "PE": {
            "LTP": 80.02,
            "OI": 334552,
            "changeInOI": 4633
          }
        },
        {
          "strikePrice": 23850,
          "isATM": false,
          "CE": {
            "LTP": 102.39,
            "OI": 124723,
            "changeInOI": -315
          },
          "PE": {
            "LTP": 151.76,
            "OI": 516372,
            "changeInOI": -2687
          }
        },
        {
          "strikePrice": 23900,
          "isATM": false,
          "CE": {
            "LTP": 29.59,
            "OI": 192839,
            "changeInOI": 2145
          },
          "PE": {
            "LTP": 191.02,
            "OI": 46227,
            "changeInOI": -2209
          }
        },
        {
          "strikePrice": 23950,
          "isATM": false,
          "CE": {
            "LTP": 0.31,
            "OI": 4495,
            "changeInOI": 4495
          },
          "PE": {
            "LTP": 192.18,
            "OI": 225507,
            "changeInOI": 2253
          }
        },
        {
          "strikePrice": 24000,
          "isATM": true,
          "CE": {
            "LTP": 43.64,
            "OI": 470835,
            "changeInOI": -3296
          },
          "PE": {
            "LTP": 19.8,
            "OI": 232514,
            "changeInOI": 4545
          }
        },
        {
          "strikePrice": 24050,
          "isATM": false,
          "CE": {
            "LTP": 60.78,
            "OI": 288399,
            "changeInOI": -53
          },
          "PE": {
            "LTP": 75.72,
            "OI": 221161,
            "changeInOI": -3821
          }
        },
        {
          "strikePrice": 24100,
          "isATM": false,
          "CE": {
            "LTP": 259.94,
            "OI": 408754,
            "changeInOI": 1365
          },
          "PE": {
            "LTP": 96.77,
            "OI": 113743,
            "changeInOI": 500
          }
        },
        {
          "strikePrice": 24150,
          "isATM": false,
          "CE": {
            "LTP": 20.47,
            "OI": 44656,
            "changeInOI": -4474
          },
          "PE": {
            "LTP": 281.84,
            "OI": 129166,
            "changeInOI": 1469
          }
        },
        {
          "strikePrice": 24200,
          "isATM": false,
          "CE": {
            "LTP": 66.26,
            "OI": 368984,
            "changeInOI": -4066
          },
          "PE": {
            "LTP": 121.01,
            "OI": 450716,
            "changeInOI": 4847
          }
        },
        {
          "strikePrice": 24250,
          "isATM": false,
          "CE": {
            "LTP": 15.53,
            "OI": 405260,
            "changeInOI": -2558
          },
          "PE": {
            "LTP": 265.4,
            "OI": 523917,
            "changeInOI": 2822
          }
        },
        {
          "strikePrice": 24300,
          "isATM": false,
          "CE": {
            "LTP": 100.93,
            "OI": 120439,
            "changeInOI": -4170
          },
          "PE": {
            "LTP": 289.09,
            "OI": 65342,
            "changeInOI": 3251
          }
        },
        {
          "strikePrice": 24350,
          "isATM": false,
          "CE": {
            "LTP": 165.37,
            "OI": 218303,
            "changeInOI": 2168
          },
          "PE": {
            "LTP": 173.05,
            "OI": 392053,
            "changeInOI": 1688
          }
        },
        {
          "strikePrice": 24400,
          "isATM": false,
          "CE": {
            "LTP": 161.32,
            "OI": 424059,
            "changeInOI": 748
          },
          "PE": {
            "LTP": 96.51,
            "OI": 482048,
            "changeInOI": 3240
          }
        },
        {
          "strikePrice": 24450,
          "isATM": false,
          "CE": {
            "LTP": 15.96,
            "OI": 424207,
            "changeInOI": 4781
          },
          "PE": {
            "LTP": 15.78,
            "OI": 27212,
            "changeInOI": 906
          }
        },
        {
          "strikePrice": 24500,
          "isATM": false,
          "CE": {
            "LTP": 159.8,
            "OI": 219596,
            "changeInOI": -666
          },
          "PE": {
            "LTP": 53.1,
            "OI": 179674,
            "changeInOI": 2777
          }
        },
        {
          "strikePrice": 24550,
          "isATM": false,
          "CE": {
            "LTP": 105.61,
            "OI": 555609,
            "changeInOI": -3726
          },
          "PE": {
            "LTP": 252.53,
            "OI": 334449,
            "changeInOI": -447
          }
        },
        {
          "strikePrice": 24600,
          "isATM": false,
          "CE": {
            "LTP": 175.37,
            "OI": 278005,
            "changeInOI": 1121
          },
          "PE": {
            "LTP": 190.07,
            "OI": 258428,
            "changeInOI": 2302
          }
        },
        {
          "strikePrice": 24650,
          "isATM": false,
          "CE": {
            "LTP": 66.27,
            "OI": 23861,
            "changeInOI": 2013
          },
          "PE": {
            "LTP": 185.68,
            "OI": 194478,
            "changeInOI": -1146
          }
        },
        {
          "strikePrice": 24700,
          "isATM": false,
          "CE": {
            "LTP": 84.49,
            "OI": 21759,
            "changeInOI": -2034
          },
          "PE": {
            "LTP": 176.1,
            "OI": 146575,
            "changeInOI": -2005
          }
        }
      ]
    },
    "BANKNIFTY": {
      "price": 48059.65,
      "time": "15:13:04",
      "optionsChain": [
        {
          "strikePrice": 46600,
          "isATM": false,
          "CE": {
            "LTP": 180.52,
            "OI": 530848,
            "changeInOI": -83
          },
          "PE": {
            "LTP": 12.54,
            "OI": 341680,
            "changeInOI": -3291
          }
        },
        {
          "strikePrice": 46700,
          "isATM": false,
          "CE": {
            "LTP": 202.19,
            "OI": 223900,
            "changeInOI": 309
          },
          "PE": {
            "LTP": 138.7,
            "OI": 81013,
            "changeInOI": 4755
          }
        },
        {
          "strikePrice": 46800,
          "isATM": false,
          "CE": {
            "LTP": 207.6,
            "OI": 333025,
            "changeInOI": 2442
          },
          "PE": {
            "LTP": 135.57,
            "OI": 70071,
            "changeInOI": 2228
          }
        },
        {
          "strikePrice": 46900,
          "isATM": false,
          "CE": {
            "LTP": 89.92,
            "OI": 223768,
            "changeInOI": -4736
          },
          "PE": {
            "LTP": 136.0,
            "OI": 156771,
            "changeInOI": -3580
          }
        },
        {
          "strikePrice": 47000,
          "isATM": false,
          "CE": {
            "LTP": 37.12,
            "OI": 197598,
            "changeInOI": -2048
          },
          "PE": {
            "LTP": 133.78,
            "OI": 74318,
            "changeInOI": 749
          }
        },
        {
          "strikePrice": 47100,
          "isATM": false,
          "CE": {
            "LTP": 72.91,
            "OI": 225907,
            "changeInOI": -3481
          },
          "PE": {
            "LTP": 214.34,
            "OI": 449627,
            "changeInOI": 1792
          }
        },
        {
          "strikePrice": 47200,
          "isATM": false,
          "CE": {
            "LTP": 354.93,
            "OI": 261386,
            "changeInOI": 4890
          },
          "PE": {
            "LTP": 250.44,
            "OI": 323877,
            "changeInOI": -3799
          }
        },
        {
          "strikePrice": 47300,
          "isATM": false,
          "CE": {
            "LTP": 65.93,
            "OI": 615158,
            "changeInOI": 4311
          },
          "PE": {
            "LTP": 25.69,
            "OI": 181378,
            "changeInOI": 1099
          }
        },
        {
          "strikePrice": 47400,
          "isATM": false,
          "CE": {
            "LTP": 193.0,
            "OI": 68011,
            "changeInOI": -2210
          },
          "PE": {
            "LTP": 124.38,
            "OI": 443752,
            "changeInOI": 2516
          }
        },
        {
          "strikePrice": 47500,
          "isATM": false,
          "CE": {
            "LTP": 113.87,
            "OI": 173892,
            "changeInOI": 4677
          },
          "PE": {
            "LTP": 202.21,
            "OI": 355564,
            "changeInOI": 3866
          }
        },
        {
          "strikePrice": 47600,
          "isATM": false,
          "CE": {
            "LTP": 138.79,
            "OI": 169359,
            "changeInOI": -846
          },
          "PE": {
            "LTP": 235.1,
            "OI": 93867,
            "changeInOI": 4018
          }
        },
        {
          "strikePrice": 47700,
          "isATM": false,
          "CE": {
            "LTP": 100.28,
            "OI": 177207,
            "changeInOI": 2117
          },
          "PE": {
            "LTP": 181.05,
            "OI": 155247,
            "changeInOI": -1080
          }
        },
        {
          "strikePrice": 47800,
          "isATM": false,
          "CE": {
            "LTP": 99.61,
            "OI": 248300,
            "changeInOI": -4624
          },
          "PE": {
            "LTP": 219.34,
            "OI": 303169,
            "changeInOI": 1020
          }
        },
        {
          "strikePrice": 47900,
          "isATM": false,
          "CE": {
            "LTP": 17.28,
            "OI": 115792,
            "changeInOI": 220
          },
          "PE": {
            "LTP": 118.87,
            "OI": 157330,
            "changeInOI": -2579
          }
        },
        {
          "strikePrice": 48000,
          "isATM": false,
          "CE": {
            "LTP": 133.88,
            "OI": 222881,
            "changeInOI": -789
          },
          "PE": {
            "LTP": 83.67,
            "OI": 342858,
            "changeInOI": -1577
          }
        },
        {
          "strikePrice": 48100,
          "isATM": true,
          "CE": {
            "LTP": 236.83,
            "OI": 406544,
            "changeInOI": -1831
          },
          "PE": {
            "LTP": 280.97,
            "OI": 128932,
            "changeInOI": 4686
          }
        },
        {
          "strikePrice": 48200,
          "isATM": false,
          "CE": {
            "LTP": 70.47,
            "OI": 426779,
            "changeInOI": 4465
          },
          "PE": {
            "LTP": 217.99,
            "OI": 411066,
            "changeInOI": 3211
          }
        },
        {
          "strikePrice": 48300,
          "isATM": false,
          "CE": {
            "LTP": 231.21,
            "OI": 312755,
            "changeInOI": 3299
          },
          "PE": {
            "LTP": 192.5,
            "OI": 493762,
            "changeInOI": -1402
          }
        },
        {
          "strikePrice": 48400,
          "isATM": false,
          "CE": {
            "LTP": 152.42,
            "OI": 226707,
            "changeInOI": -1080
          },
          "PE": {
            "LTP": 172.15,
            "OI": 504273,
            "changeInOI": -4229
          }
        },
        {
          "strikePrice": 48500,
          "isATM": false,
          "CE": {
            "LTP": 113.99,
            "OI": 88428,
            "changeInOI": 938
          },
          "PE": {
            "LTP": 20.01,
            "OI": 583107,
            "changeInOI": -1014
          }
        },
        {
          "strikePrice": 48600,
          "isATM": false,
          "CE": {
            "LTP": 2.23,
            "OI": 378146,
            "changeInOI": -2215
          },
          "PE": {
            "LTP": 148.82,
            "OI": 447540,
            "changeInOI": -856
          }
        },
        {
          "strikePrice": 48700,
          "isATM": false,
          "CE": {
            "LTP": 106.62,
            "OI": 202230,
            "changeInOI": 279
          },
          "PE": {
            "LTP": 41.35,
            "OI": 433161,
            "changeInOI": 4497
          }
        },
        {
          "strikePrice": 48800,
          "isATM": false,
          "CE": {
            "LTP": 221.03,
            "OI": 27074,
            "changeInOI": 3834
          },
          "PE": {
            "LTP": 119.21,
            "OI": 147252,
            "changeInOI": -2410
          }
        },
        {
          "strikePrice": 48900,
          "isATM": false,
          "CE": {
            "LTP": 110.11,
            "OI": 478136,
            "changeInOI": 1604
          },
          "PE": {
            "LTP": 186.99,
            "OI": 184494,
            "changeInOI": -436
          }
        },
        {
          "strikePrice": 49000,
          "isATM": false,
          "CE": {
            "LTP": 277.35,
            "OI": 179077,
            "changeInOI": 4665
          },
          "PE": {
            "LTP": 189.26,
            "OI": 252393,
            "changeInOI": -470
          }
        },
        {
          "strikePrice": 49100,
          "isATM": false,
          "CE": {
            "LTP": 103.83,
            "OI": 482937,
            "changeInOI": -4443
          },
          "PE": {
            "LTP": 114.25,
            "OI": 192162,
            "changeInOI": -3670
          }
        },
        {
          "strikePrice": 49200,
          "isATM": false,
          "CE": {
            "LTP": 71.02,
            "OI": 339999,
            "changeInOI": 3239
          },
          "PE": {
            "LTP": 43.62,
            "OI": 457960,
            "changeInOI": 4132
          }
        },
        {
          "strikePrice": 49300,
          "isATM": false,
          "CE": {
            "LTP": 103.39,
            "OI": 426070,
            "changeInOI": -2420
          },
          "PE": {
            "LTP": 43.55,
            "OI": 312287,
            "changeInOI": 1763
          }
        },
        {
          "strikePrice": 49400,
          "isATM": false,
          "CE": {
            "LTP": 112.3,
            "OI": 5798,
            "changeInOI": -2412
          },
          "PE": {
            "LTP": 29.76,
            "OI": 403539,
            "changeInOI": -4127
          }
        },
        {
          "strikePrice": 49500,
          "isATM": false,
          "CE": {
            "LTP": 107.79,
            "OI": 222988,
            "changeInOI": 1906
          },
          "PE": {
            "LTP": 48.87,
            "OI": 56371,
            "changeInOI": -4534
          }
        }
      ]
    }
  }
}